pychronic/__init__.py
pychronic/enums.py
pychronic/tagger.py
pychronic/utils.py
pychronic/models/__init__.py
pychronic/models/data_types.py
pychronic/models/parse_pattern.py
pychronic/models/parsed_input.py
pychronic/models/tagged_word.py
tests/__init__.py
tests/test_tagger.py
tests/test_utils.py
pychronic-0.0.14.dist-info/METADATA
pychronic-0.0.14.dist-info/WHEEL
pychronic-0.0.14.dist-info/top_level.txt
pychronic-0.0.14.dist-info/RECORD
