Metadata-Version: 2.1
Name: pychronic
Version: 0.0.14
Summary: A library to convert datetime to natural human readable format
Home-page: UNKNOWN
Author: jayeshathila
Author-email: sharma.jayesh52@gmail.com
License: MIT
Platform: UNKNOWN
Classifier: Programming Language :: Python :: 3
Classifier: License :: OSI Approved :: MIT License
Classifier: Operating System :: OS Independent
Requires-Dist: requests
Provides-Extra: test
Requires-Dist: pytest ; extra == 'test'
Requires-Dist: pytest-runner ; extra == 'test'
Requires-Dist: pytest-cov ; extra == 'test'
Requires-Dist: pytest-pep8 ; extra == 'test'
